[{"name":"fr","value":"1SeFQndDW6D7zrhzA.AWXnAPtPqOo9dFU7IUgff4v2UfY.Bgvy69.r7.AAA.0.0.Bgvy7H.AWV4nL5Z3RI","domain":".facebook.com","path":"/","expires":1630918083.182427,"size":84,"httpOnly":true,"secure":true,"session":false,"sameSite":"None","sameParty":false,"sourceScheme":"Secure","sourcePort":443},{"name":"xs","value":"6%3A75fF80Btb2H1ow%3A2%3A1623142087%3A-1%3A-1","domain":".facebook.com","path":"/","expires":1654678086.182352,"size":47,"httpOnly":true,"secure":true,"session":false,"sameSite":"None","sameParty":false,"sourceScheme":"Secure","sourcePort":443},{"name":"datr","value":"vS6_YMUSM1yJfJ2r5P6ZKtsO","domain":".facebook.com","path":"/","expires":1686214079.408127,"size":28,"httpOnly":true,"secure":true,"session":false,"sameSite":"None","sameParty":false,"sourceScheme":"Secure","sourcePort":443},{"name":"c_user","value":"100069126042424","domain":".facebook.com","path":"/","expires":1654678086.182269,"size":21,"httpOnly":false,"secure":true,"session":false,"sameSite":"None","sameParty":false,"sourceScheme":"Secure","sourcePort":443},{"name":"spin","value":"r.1003923158_b.trunk_t.1623142089_s.1_v.2_","domain":".facebook.com","path":"/","expires":1623232089.935237,"size":46,"httpOnly":true,"secure":true,"session":false,"sameSite":"None","sameParty":false,"sourceScheme":"Secure","sourcePort":443},{"name":"wd","value":"1366x613","domain":".facebook.com","path":"/","expires":1623746885,"size":10,"httpOnly":false,"secure":true,"session":false,"sameSite":"Lax","sameParty":false,"sourceScheme":"Secure","sourcePort":443},{"name":"sb","value":"vS6_YCvViAyVLgSkmCocXj4J","domain":".facebook.com","path":"/","expires":1686214089.182116,"size":26,"httpOnly":true,"secure":true,"session":false,"sameSite":"None","sameParty":false,"sourceScheme":"Secure","sourcePort":443}]